sio_sso_lib/__init__.py
sio_sso_lib/main.py
sio_sso_lib-0.1.3.dist-info/METADATA
sio_sso_lib-0.1.3.dist-info/WHEEL
sio_sso_lib-0.1.3.dist-info/top_level.txt
sio_sso_lib-0.1.3.dist-info/RECORD
